ProcessLock/Locker.py
ProcessLock/__init__.py
ProcessLock-1.0.3.dist-info/LICENSE
ProcessLock-1.0.3.dist-info/METADATA
ProcessLock-1.0.3.dist-info/WHEEL
ProcessLock-1.0.3.dist-info/top_level.txt
ProcessLock-1.0.3.dist-info/RECORD
