Metadata-Version: 2.1
Name: ProcessLock
Version: 1.0.3
Summary: Python全局进程锁,文件锁!
Home-page: https://github.com/EVA-JianJun/ProcessLock
Author: jianjun
Author-email: 910667956@qq.com
License-File: LICENSE
Requires-Dist: portalocker >=1.6.0
